ColourLogger/__init__.py
ColourLogger/colorize.py
ColourLogger/extensions.py
ColourLogger/logger.py
ColourLogger-2022.12.14.dist-info/LICENSE
ColourLogger-2022.12.14.dist-info/METADATA
ColourLogger-2022.12.14.dist-info/WHEEL
ColourLogger-2022.12.14.dist-info/top_level.txt
ColourLogger-2022.12.14.dist-info/RECORD
