Metadata-Version: 2.1
Name: ColourLogger
Version: 2022.12.14
Summary: A small package designed to colorize your console log.
Author-email: Edel Perez <matoih@outlook.com>
Project-URL: Homepage, https://github.com/edel-p/ColourLogger
Project-URL: Bug Tracker, https://github.com/edel-p/ColourLogger/issues
Classifier: Programming Language :: Python :: 3
Classifier: License :: OSI Approved :: MIT License
Classifier: Operating System :: OS Independent
Requires-Python: >=3.8
License-File: LICENSE
